<TrID ver="2.00">
	<Info>
		<FileType>Project Dogwaffle layered bitmap</FileType>
		<Ext>LYR</Ext>
		<ExtraInfo>
			<Rem>Project Dogwaffle is a paint and animation software.</Rem>
			<RefURL>http://www.thebest3d.com/dogwaffle</RefURL>
		</ExtraInfo>
		<User>Marco Pontello</User>
		<E-Mail>marcopon@gmail.com</E-Mail>
		<Home>http://mark0.net</Home>
	</Info>
	<General>
		<FileNum>7</FileNum>
		<Date>
			<Year>2005</Year>
			<Month>08</Month>
			<Day>21</Day>
		</Date>
		<Time>
			<Hour>20</Hour>
			<Min>19</Min>
			<Sec>03</Sec>
		</Time>
		<Creator>TrIDScan32 v1.56</Creator>
	</General>
	<FrontBlock>
		<Pattern>
			<Bytes>4C595232</Bytes>
			<ASCII> L Y R 2</ASCII>
			<Pos>0</Pos>
		</Pattern>
	</FrontBlock>
</TrID>
