<TrID ver="2.00">
	<Info>
		<FileType>Harvard Graphics Chart(v3.0)</FileType>
		<Ext>CH3</Ext>
		<ExtraInfo>
			<Rem></Rem>
			<RefURL>http://en.wikipedia.org/wiki/Harvard_Graphics</RefURL>
		</ExtraInfo>
		<User>Marco Pontello</User>
		<E-Mail>marcopon@gmail.com</E-Mail>
		<Home>http://mark0.net</Home>
	</Info>
	<General>
		<FileNum>4</FileNum>
		<Date>
			<Year>2008</Year>
			<Month>10</Month>
			<Day>07</Day>
		</Date>
		<Time>
			<Hour>17</Hour>
			<Min>26</Min>
			<Sec>48</Sec>
		</Time>
		<Creator>TrIDScan32 v1.56</Creator>
	</General>
	<FrontBlock>
		<Pattern>
			<Bytes>48474233</Bytes>
			<ASCII> H G B 3</ASCII>
			<Pos>0</Pos>
		</Pattern>
	</FrontBlock>
</TrID>
