<TrID ver="2.00">
	<Info>
		<FileType>Microsoft App-V Sequencer Differential SFT</FileType>
		<Ext>DSFT</Ext>
		<ExtraInfo>
			<Rem></Rem>
			<RefURL>http://en.wikipedia.org/wiki/Microsoft_App-V</RefURL>
		</ExtraInfo>
		<User>Marco Pontello</User>
		<E-Mail>marcopon@gmail.com</E-Mail>
		<Home>http://mark0.net</Home>
	</Info>
	<General>
		<FileNum>2</FileNum>
		<Date>
			<Year>2012</Year>
			<Month>9</Month>
			<Day>18</Day>
		</Date>
		<Time>
			<Hour>3</Hour>
			<Min>53</Min>
			<Sec>32</Sec>
		</Time>
		<Creator>TrIDScan/Py v1.80</Creator>
	</General>
	<FrontBlock>
		<Pattern>
			<Bytes>44534654</Bytes>
			<ASCII> D S F T</ASCII>
			<Pos>0</Pos>
		</Pattern>
	</FrontBlock>
</TrID>