<TrID ver="2.00">
	<Info>
		<FileType>AutoCAD 2010-2011 drawing</FileType>
		<Ext>DWG</Ext>
		<ExtraInfo>
			<Rem></Rem>
			<RefURL>http://www.autodesk.com</RefURL>
		</ExtraInfo>
		<User>Marco Pontello</User>
		<E-Mail>marcopon@gmail.com</E-Mail>
		<Home>http://mark0.net</Home>
	</Info>
	<General>
		<FileNum>2</FileNum>
		<Date>
			<Year>2011</Year>
			<Month>2</Month>
			<Day>2</Day>
		</Date>
		<Time>
			<Hour>15</Hour>
			<Min>8</Min>
			<Sec>1</Sec>
		</Time>
		<Creator>TrIDScan/Py v1.79.6b</Creator>
	</General>
	<FrontBlock>
		<Pattern>
			<Bytes>414331303234</Bytes>
			<ASCII> A C 1 0 2 4</ASCII>
			<Pos>0</Pos>
		</Pattern>
	</FrontBlock>
</TrID>