<TrID ver="2.00">
	<Info>
		<FileType>FMOD Designer Project</FileType>
		<Ext>FDP</Ext>
		<ExtraInfo>
			<Rem>FMOD is a multiplatform commercial audio library by Firelight Technologies.</Rem>
			<RefURL>http://www.fmod.org/</RefURL>
		</ExtraInfo>
		<User>Marco Pontello</User>
		<E-Mail>marcopon@gmail.com</E-Mail>
		<Home>http://mark0.net</Home>
	</Info>
	<General>
		<FileNum>9</FileNum>
		<Refine>2 by Marco Pontello</Refine>
		<CheckStrings>True</CheckStrings>
		<Date>
			<Year>2011</Year>
			<Month>3</Month>
			<Day>31</Day>
		</Date>
		<Time>
			<Hour>17</Hour>
			<Min>11</Min>
			<Sec>11</Sec>
		</Time>
		<Creator>TrIDScan/Py v1.79.11b</Creator>
	</General>
	<FrontBlock>
		<Pattern>
			<Bytes>3C70726F6A6563743E0D0A3C6E616D653E</Bytes>
			<ASCII> . p r o j e c t . . . . n a m e</ASCII>
			<Pos>0</Pos>
		</Pattern>
	</FrontBlock>
	<GlobalStrings>
		<String>TEMPLATE_PROP_X_3D_CONE_OUTSIDE_VOLUME</String>
		<String>TEMPLATE_PROP_X_3D_CONE_OUTSIDE_ANGLE</String>
		<String>TEMPLATE_PROP_MAX_PLAYBACKS_BEHAVIOR</String>
		<String>TEMPLATE_PROP_X_3D_CONE_INSIDE_ANGLE</String>
		<String>TEMPLATE_PROP_X_3D_DOPPLER_FACTOR</String>
		<String>TEMPLATE_PROP_X_3D_SPEAKER_SPREAD</String>
		<String>TEMPLATE_PROP_X_3D_MAX_DISTANCE</String>
		<String>TEMPLATE_PROP_X_3D_MIN_DISTANCE</String>
		<String>TEMPLATE_PROP_X_2D_SPEAKER_LR</String>
		<String>TEMPLATE_PROP_X_2D_SPEAKER_LS</String>
		<String>TEMPLATE_PROP_X_2D_SPEAKER_RR</String>
		<String>TEMPLATE_PROP_X_2D_SPEAKER_RS</String>
		<String>_XBOX360_AUDIOSOURCEDIRECTORY</String>
		<String>TEMPLATE_PROP_X_2D_SPEAKER_C</String>
		<String>TEMPLATE_PROP_X_3D_PAN_LEVEL</String>
		<String>TEMPLATE_PROP_X_3D_POSITION</String>
		<String>TEMPLATE_PROP_X_SPEAKER_LFE</String>
		<String>TEMPLATE_PROP_FADEOUT_TIME</String>
		<String>TEMPLATE_PROP_X_3D_ROLLOFF</String>
		<String>_XBOX_AUDIOSOURCEDIRECTORY</String>
		<String>TEMPLATE_PROP_FADEIN_TIME</String>
		<String>_PS2_AUDIOSOURCEDIRECTORY</String>
		<String>_PS3_AUDIOSOURCEDIRECTORY</String>
		<String>_PSP_AUDIOSOURCEDIRECTORY</String>
		<String>_WII_AUDIOSOURCEDIRECTORY</String>
		<String>NEWEVENTLASTTEMPLATENAME</String>
		<String>_GC_AUDIOSOURCEDIRECTORY</String>
		<String>_PC_AUDIOSOURCEDIRECTORY</String>
		<String>_XBOX360_BUILDDIRECTORY</String>
		<String>BUILD_PROGRAMMERREPORT</String>
		<String>TEMPLATE_PROP_PRIORITY</String>
		<String>_XBOX360_ENCRYPTIONKEY</String>
		<String>_XBOX360_FORCESOFTWARE</String>
		<String>CONE_OUTSIDE_VOLUMEDB</String>
		<String>MAXPLAYBACKS_BEHAVIOR</String>
		<String>TEMPLATE_PROP_ONESHOT</String>
		<String>TEMPLATE_PROP_REVERB_</String>
		<String>TEMPLATE_PROP_VOLUME</String>
		<String>_XBOX_BUILDDIRECTORY</String>
		<String>NEWEVENTUSETEMPLATE</String>
		<String>TEMPLATE_PROP_NOTES</String>
		<String>TEMPLATE_PROP_PITCH</String>
		<String>_PS2_BUILDDIRECTORY</String>
		<String>_PS3_BUILDDIRECTORY</String>
		<String>_PSP_BUILDDIRECTORY</String>
		<String>_WII_BUILDDIRECTORY</String>
		<String>_XBOX360_MAXSTREAMS</String>
		<String>_XBOX_ENCRYPTIONKEY</String>
		<String>_XBOX_FORCESOFTWARE</String>
		<String>AUTOPITCHREFERENCE</String>
		<String>DECOMPRESSEDSAMPLE</String>
		<String>TEMPLATE_PROP_MODE</String>
		<String>_GC_BUILDDIRECTORY</String>
		<String>_PC_BUILDDIRECTORY</String>
		<String>_PS2_ENCRYPTIONKEY</String>
		<String>_PS2_FORCESOFTWARE</String>
		<String>_PS3_ENCRYPTIONKEY</String>
		<String>_PS3_FORCESOFTWARE</String>
		<String>_PSP_ENCRYPTIONKEY</String>
		<String>_PSP_FORCESOFTWARE</String>
		<String>_WII_ENCRYPTIONKEY</String>
		<String>_WII_FORCESOFTWARE</String>
		<String>EVENTGROUP_NEXTID</String>
		<String>SPEAKER_PAN_THETA</String>
		<String>VOLUME_RANDOM_MAX</String>
		<String>VOLUME_RANDOM_MIN</String>
		<String>_GC_ENCRYPTIONKEY</String>
		<String>_GC_FORCESOFTWARE</String>
		<String>_PC_ENCRYPTIONKEY</String>
		<String>_PC_FORCESOFTWARE</String>
		<String>AUTOPITCHENABLED</String>
		<String>BUILD_HEADERFILE</String>
		<String>CONTROLPARAMETER</String>
		<String>PARAMETER_NEXTID</String>
		<String>PITCH_RANDOM_MAX</String>
		<String>PITCH_RANDOM_MIN</String>
		<String>SOUNDBANK_NEXTID</String>
		<String>_XBOX360_QUALITY</String>
		<String>_XBOX_MAXSTREAMS</String>
		<String>CURRENTPLATFORM</String>
		<String>ENVELOPE_NEXTID</String>
		<String>SOUNDDEF_NEXTID</String>
		<String>_PS2_MAXSTREAMS</String>
		<String>_PS3_MAXSTREAMS</String>
		<String>_PSP_MAXSTREAMS</String>
		<String>_WII_MAXSTREAMS</String>
		<String>_XBOX360_FORMAT</String>
		<String>CAR_LOADSMOOTH</String>
		<String>REVERBLEVEL_DB</String>
		<String>SPEAKER_CONFIG</String>
		<String>WORLD_RELATIVE</String>
		<String>_GC_MAXSTREAMS</String>
		<String>_PC_MAXSTREAMS</String>
		<String>BUILD_PROJECT</String>
		<String>CAR_LOADSCALE</String>
		<String>CAR_RPMSMOOTH</String>
		<String>DOPPLER_SCALE</String>
		<String>EVENTCATEGORY</String>
		<String>SOUNDBANKNAME</String>
		<String>SPAWNTIME_MAX</String>
		<String>SPAWNTIME_MIN</String>
		<String>SPEAKER_PAN_R</String>
		<String>_XBOX_QUALITY</String>
		<String>EVENT_NEXTID</String>
		<String>HEADRELATIVE</String>
		<String>LAYER_NEXTID</String>
		<String>RANGESPACING</String>
		<String>STEAL_OLDEST</String>
		<String>_PS2_QUALITY</String>
		<String>_PS3_QUALITY</String>
		<String>_PSP_QUALITY</String>
		<String>_WII_QUALITY</String>
		<String>_XBOX_FORMAT</String>
		<String>CURRENTBANK</String>
		<String>MAXDISTANCE</String>
		<String>MINDISTANCE</String>
		<String>_GC_QUALITY</String>
		<String>_PC_QUALITY</String>
		<String>_PS2_FORMAT</String>
		<String>_PS3_FORMAT</String>
		<String>_PSP_FORMAT</String>
		<String>_WII_FORMAT</String>
		<String>ISTEMPLATE</String>
		<String>PANLEVEL3D</String>
		<String>RANGEUNITS</String>
		<String>SEQUENTIAL</String>
		<String>SPEAKER_LB</String>
		<String>SPEAKER_RB</String>
		<String>_GC_FORMAT</String>
		<String>_PC_FORMAT</String>
		<String>SEEKSPEED</String>
		<String>SOUNDLOCK</String>
		<String>SPAWN_MAX</String>
		<String>VOLUME_DB</String>
		<String>BANKTYPE</String>
		<String>FILENAME</String>
		<String>FINETUNE</String>
		<String>LOOPMODE</String>
		<String>RANGEMAX</String>
		<String>RANGEMIN</String>
		<String>VELOCITY</String>
		<String>WAVEFORM</String>
		<String>DEFFREQ</String>
		<String>ENVLOCK</String>
		<String>LAYER00</String>
		<String>PRIMARY</String>
		<String>REBUILD</String>
		<String>VERSION</String>
		<String>_DIALOG</String>
		<String>DEFPAN</String>
		<String>DEFPRI</String>
		<String>DEFVOL</String>
		<String>HEIGHT</String>
		<String>WEIGHT</String>
		<String>MUSIC</String>
		<String>START</String>
		<String>WIDTH</String>
		<String>CHAT</String>
		<String>KING</String>
		<String>MENT</String>
		<String>MUTE</String>
		<String>OPEN</String>
		<String>SYNC</String>
		<String>_INT</String>
	</GlobalStrings>
</TrID>