<TrID ver="2.00">
	<Info>
		<FileType>Gambit Normal Form representation</FileType>
		<Ext>NFG</Ext>
		<ExtraInfo>
			<Rem>Gambit is a library of game theory software and tools for the construction and analysis of finite extensive and normal form games.</Rem>
			<RefURL>http://econweb.tamu.edu/gambit/</RefURL>
		</ExtraInfo>
		<User>Marco Pontello</User>
		<E-Mail>marcopon@gmail.com</E-Mail>
		<Home>http://mark0.net</Home>
	</Info>
	<General>
		<FileNum>49</FileNum>
		<Date>
			<Year>2005</Year>
			<Month>12</Month>
			<Day>03</Day>
		</Date>
		<Time>
			<Hour>16</Hour>
			<Min>24</Min>
			<Sec>43</Sec>
		</Time>
		<Creator>TrIDScan32 v1.56</Creator>
	</General>
	<FrontBlock>
		<Pattern>
			<Bytes>4E464720</Bytes>
			<ASCII> N F G</ASCII>
			<Pos>0</Pos>
		</Pattern>
		<Pattern>
			<Bytes>20</Bytes>
			<Pos>5</Pos>
		</Pattern>
		<Pattern>
			<Bytes>2022</Bytes>
			<ASCII>   "</ASCII>
			<Pos>7</Pos>
		</Pattern>
	</FrontBlock>
</TrID>
