<TrID ver="2.00">
	<Info>
		<FileType>GEM metafile</FileType>
		<Ext>GEM</Ext>
		<ExtraInfo>
			<Rem></Rem>
			<RefURL>http://en.wikipedia.org/wiki/Graphical_Environment_Manager</RefURL>
		</ExtraInfo>
		<User>Marco Pontello</User>
		<E-Mail>marcopon@gmail.com</E-Mail>
		<Home>http://mark0.net</Home>
	</Info>
	<General>
		<FileNum>8</FileNum>
		<Refine>4 by Marco Pontello</Refine>
		<Date>
			<Year>2011</Year>
			<Month>3</Month>
			<Day>28</Day>
		</Date>
		<Time>
			<Hour>17</Hour>
			<Min>51</Min>
			<Sec>59</Sec>
		</Time>
		<Creator>TrIDScan/Py v1.79.11b</Creator>
	</General>
	<FrontBlock>
		<Pattern>
			<Bytes>FFFF18</Bytes>
			<Pos>0</Pos>
		</Pattern>
	</FrontBlock>
</TrID>