<TrID ver="2.00">
	<Info>
		<FileType>Google Earth network link</FileType>
		<Ext>KML</Ext>
		<ExtraInfo>
			<Rem></Rem>
			<RefURL>http://en.wikipedia.org/wiki/Keyhole_Markup_Language</RefURL>
		</ExtraInfo>
		<User>Marco Pontello</User>
		<E-Mail>marcopon@gmail.com</E-Mail>
		<Home>http://mark0.net</Home>
	</Info>
	<General>
		<FileNum>12</FileNum>
		<CheckStrings>True</CheckStrings>
		<Date>
			<Year>2008</Year>
			<Month>07</Month>
			<Day>15</Day>
		</Date>
		<Time>
			<Hour>19</Hour>
			<Min>06</Min>
			<Sec>04</Sec>
		</Time>
		<Creator>TrIDScan32 v1.56</Creator>
	</General>
	<FrontBlock>
		<Pattern>
			<Bytes>3C3F786D6C2076657273696F6E3D22312E3022</Bytes>
			<ASCII> . ? x m l   v e r s i o n = " 1 . 0 "</ASCII>
			<Pos>0</Pos>
		</Pattern>
	</FrontBlock>
	<GlobalStrings>
		<String>EARTH.GOOGLE.COM</String>
		<String>NETWORKLINK</String>
		<String>XML VERSION</String>
		<String>KML XMLNS</String>
		<String>NAME</String>
		<String>HREF</String>
		<String>HTTP</String>
	</GlobalStrings>
</TrID>
