<TrID ver="2.00">
	<Info>
		<FileType>Linden Lab Structured Data</FileType>
		<Ext>LLSD</Ext>
		<ExtraInfo>
			<Rem></Rem>
			<RefURL>http://en.wikipedia.org/wiki/Linden_Lab</RefURL>
		</ExtraInfo>
		<User>Marco Pontello</User>
		<E-Mail>marcopon@gmail.com</E-Mail>
		<Home>http://mark0.net</Home>
	</Info>
	<General>
		<FileNum>6</FileNum>
		<Date>
			<Year>2008</Year>
			<Month>06</Month>
			<Day>04</Day>
		</Date>
		<Time>
			<Hour>00</Hour>
			<Min>27</Min>
			<Sec>40</Sec>
		</Time>
		<Creator>TrIDScan32 v1.56</Creator>
	</General>
	<FrontBlock>
		<Pattern>
			<Bytes>3C6C6C73643E</Bytes>
			<ASCII> . l l s d</ASCII>
			<Pos>0</Pos>
		</Pattern>
	</FrontBlock>
</TrID>
