<TrID ver="2.00">
	<Info>
		<FileType>LEGO Exchange Format - Digital Designer</FileType>
		<Ext>LXF</Ext>
		<ExtraInfo>
			<Rem></Rem>
			<RefURL>http://ldd.lego.com/en-us/gallery/</RefURL>
		</ExtraInfo>
		<User>Marco Pontello</User>
		<E-Mail>marcopon@gmail.com</E-Mail>
		<Home>http://mark0.net</Home>
	</Info>
	<General>
		<FileNum>19</FileNum>
		<Date>
			<Year>2012</Year>
			<Month>8</Month>
			<Day>17</Day>
		</Date>
		<Time>
			<Hour>2</Hour>
			<Min>21</Min>
			<Sec>25</Sec>
		</Time>
		<Creator>TrIDScan/Py v1.80</Creator>
	</General>
	<FrontBlock>
		<Pattern>
			<Bytes>504B0304</Bytes>
			<ASCII> P K</ASCII>
			<Pos>0</Pos>
		</Pattern>
	</FrontBlock>
	<GlobalStrings>
		<String>IMAGE100.LXFMLPK</String>
		<String>IMAGE100.PNGPK</String>
	</GlobalStrings>
</TrID>