<TrID ver="2.00">
	<Info>
		<FileType>PowerBASIC/DOS configuration file</FileType>
		<Ext>PB</Ext>
		<ExtraInfo>
			<Rem></Rem>
			<RefURL>http://www.powerbasic.com</RefURL>
		</ExtraInfo>
		<User>Marco Pontello</User>
		<E-Mail>marcopon@gmail.com</E-Mail>
		<Home>http://mark0.net</Home>
	</Info>
	<General>
		<FileNum>2</FileNum>
		<Date>
			<Year>2008</Year>
			<Month>05</Month>
			<Day>22</Day>
		</Date>
		<Time>
			<Hour>14</Hour>
			<Min>13</Min>
			<Sec>33</Sec>
		</Time>
		<Creator>TrIDScan32 v1.56</Creator>
	</General>
	<FrontBlock>
		<Pattern>
			<Bytes>506F776572426173696320436F6E66696775726174696F6E2046696C65201A</Bytes>
			<ASCII> P o w e r B a s i c   C o n f i g u r a t i o n   F i l e</ASCII>
			<Pos>0</Pos>
		</Pattern>
	</FrontBlock>
</TrID>
