<TrID ver="2.00">
	<Info>
		<FileType>Quartus DataBase Info</FileType>
		<Ext>DB_INFO</Ext>
		<ExtraInfo>
			<Rem></Rem>
			<RefURL>http://en.wikipedia.org/wiki/Altera_Quartus</RefURL>
		</ExtraInfo>
		<User>Marco Pontello</User>
		<E-Mail>marcopon@gmail.com</E-Mail>
		<Home>http://mark0.net</Home>
	</Info>
	<General>
		<FileNum>7</FileNum>
		<CheckStrings>True</CheckStrings>
		<Date>
			<Year>2013</Year>
			<Month>12</Month>
			<Day>4</Day>
		</Date>
		<Time>
			<Hour>1</Hour>
			<Min>55</Min>
			<Sec>37</Sec>
		</Time>
		<Creator>TrIDScan/Py v1.90</Creator>
	</General>
	<FrontBlock>
		<Pattern>
			<Bytes>517561727475735F56657273696F6E203D2056657273696F6E20</Bytes>
			<ASCII> Q u a r t u s _ V e r s i o n   =   V e r s i o n</ASCII>
			<Pos>0</Pos>
		</Pattern>
	</FrontBlock>
	<GlobalStrings>
		<String>CREATION_TIME</String>
		<String>BUILD</String>
	</GlobalStrings>
</TrID>