<TrID ver="2.00">
	<Info>
		<FileType>Rapport Script</FileType>
		<Ext>RSP</Ext>
		<ExtraInfo>
			<Rem></Rem>
			<RefURL>http://www.wyse.com/products/software/rapport.asp</RefURL>
		</ExtraInfo>
		<User>Marco Pontello</User>
		<E-Mail>marcopon@gmail.com</E-Mail>
		<Home>http://mark0.net</Home>
	</Info>
	<General>
		<FileNum>2</FileNum>
		<CheckStrings>True</CheckStrings>
		<Date>
			<Year>2009</Year>
			<Month>05</Month>
			<Day>03</Day>
		</Date>
		<Time>
			<Hour>22</Hour>
			<Min>52</Min>
			<Sec>49</Sec>
		</Time>
		<Creator>TrIDScan32 v1.56</Creator>
	</General>
	<FrontBlock>
		<Pattern>
			<Bytes>5B56657273696F6E5D0D0A4E756D6265723D</Bytes>
			<ASCII> [ V e r s i o n ] . . N u m b e r =</ASCII>
			<Pos>0</Pos>
		</Pattern>
	</FrontBlock>
	<GlobalStrings>
		<String>WISARDENVIRONMENT</String>
		<String>%IMAGEWRITE%</String>
		<String>DESCRIPTION</String>
		<String>RAPPORTITF</String>
		<String>USE_REMOTE</String>
		<String>BOOTFLOPPY</String>
		<String>IMAGESIZE</String>
		<String>RTIUPROTO</String>
		<String>RTIRPROTO</String>
		<String>CATEGORY</String>
		<String>RTIRPORT</String>
		<String>ROOT.I2U</String>
		<String>RTILPROT</String>
		<String>RTILPORT</String>
		<String>FUNCTION</String>
		<String>PRODROOT</String>
		<String>USE_PXE</String>
		<String>ENVROOT</String>
		<String>ARCHIVE</String>
		<String>ENVPATH</String>
		<String>RTILDEL</String>
		<String>INVERSE</String>
		<String>PRODUCT</String>
		<String>RTIRDEL</String>
		<String>REGROOT</String>
		<String>COMMAND</String>
		<String>VERSION</String>
		<String>NUMBER</String>
		<String>TOOLS</String>
		<String>XLATE</String>
		<String>.I2C</String>
		<String>PULL</String>
		<String>PUSH</String>
	</GlobalStrings>
</TrID>
