<TrID ver="2.00">
	<Info>
		<FileType>Simple User Interface Toolkit library</FileType>
		<Ext>SUI</Ext>
		<ExtraInfo>
			<Rem></Rem>
			<RefURL></RefURL>
		</ExtraInfo>
		<User>Marco Pontello</User>
		<E-Mail>marcopon@gmail.com</E-Mail>
		<Home>http://mark0.net</Home>
	</Info>
	<General>
		<FileNum>6</FileNum>
		<Date>
			<Year>2005</Year>
			<Month>05</Month>
			<Day>05</Day>
		</Date>
		<Time>
			<Hour>12</Hour>
			<Min>43</Min>
			<Sec>30</Sec>
		</Time>
		<Creator>TrIDScan32 v1.56</Creator>
	</General>
	<FrontBlock>
		<Pattern>
			<Bytes>2F2A20535549542076657273696F6E20</Bytes>
			<ASCII> / *   S U I T   v e r s i o n</ASCII>
			<Pos>0</Pos>
		</Pattern>
		<Pattern>
			<Bytes>2E</Bytes>
			<Pos>17</Pos>
		</Pattern>
	</FrontBlock>
</TrID>
