<TrID ver="2.00">
	<Info>
		<FileType>Black and White 2 Wall data</FileType>
		<Ext>WAL</Ext>
		<ExtraInfo>
			<Rem></Rem>
			<RefURL>http://en.wikipedia.org/wiki/Black_%26_White_2</RefURL>
		</ExtraInfo>
		<User>Marco Pontello</User>
		<E-Mail>marcopon@gmail.com</E-Mail>
		<Home>http://mark0.net</Home>	</Info>
	<General>
		<FileNum>9</FileNum>
		<Date>
			<Year>2007</Year>
			<Month>11</Month>
			<Day>27</Day>
		</Date>
		<Time>
			<Hour>17</Hour>
			<Min>34</Min>
			<Sec>36</Sec>
		</Time>
		<Creator>TrIDScan32 v1.56</Creator>
	</General>
	<FrontBlock>
		<Pattern>
			<Bytes>4C694F6E4865416457616C6C56657273696F6E</Bytes>
			<ASCII> L i O n H e A d W a l l V e r s i o n</ASCII>
			<Pos>0</Pos>
		</Pattern>
		<Pattern>
			<Bytes>57616C6C</Bytes>
			<ASCII> W a l l</ASCII>
			<Pos>48</Pos>
		</Pattern>
	</FrontBlock>
</TrID>
